LICENSE
README.md
setup.cfg
setup.py
demeter/__init__.py
demeter/_typing.py
demeter/aave/__init__.py
demeter/aave/_typing.py
demeter/aave/core.py
demeter/aave/helper.py
demeter/aave/market.py
demeter/broker/__init__.py
demeter/broker/_typing.py
demeter/broker/broker.py
demeter/broker/market.py
demeter/broker/prep_market.py
demeter/core/__init__.py
demeter/core/_typing.py
demeter/core/actuator.py
demeter/core/backtest.py
demeter/data/__init__.py
demeter/data/data_cache.py
demeter/deribit/__init__.py
demeter/deribit/_typing.py
demeter/deribit/helper.py
demeter/deribit/market.py
demeter/gmx/__init__.py
demeter/gmx/_typing.py
demeter/gmx/_typing2.py
demeter/gmx/helper.py
demeter/gmx/helper2.py
demeter/gmx/market.py
demeter/gmx/market2_lp.py
demeter/gmx/market2_prep.py
demeter/gmx/utils.py
demeter/gmx/gmx_v2/__init__.py
demeter/gmx/gmx_v2/_typing.py
demeter/gmx/gmx_v2/utils.py
demeter/gmx/gmx_v2/deposit/ExecuteDepositUtils.py
demeter/gmx/gmx_v2/deposit/__init__.py
demeter/gmx/gmx_v2/market/MarketUtils.py
demeter/gmx/gmx_v2/market/__init__.py
demeter/gmx/gmx_v2/order/DecreaseOrderUtils.py
demeter/gmx/gmx_v2/order/ExecuteOrderUtils.py
demeter/gmx/gmx_v2/order/IncreaseOrderUtils.py
demeter/gmx/gmx_v2/order/SwapOrderUtils.py
demeter/gmx/gmx_v2/order/__init__.py
demeter/gmx/gmx_v2/position/BaseOrderUtils.py
demeter/gmx/gmx_v2/position/DecreasePositionCollateralUtils.py
demeter/gmx/gmx_v2/position/DecreasePositionSwapUtils.py
demeter/gmx/gmx_v2/position/DecreasePositionUtils.py
demeter/gmx/gmx_v2/position/IncreasePositionUtils.py
demeter/gmx/gmx_v2/position/Position.py
demeter/gmx/gmx_v2/position/PositionUtils.py
demeter/gmx/gmx_v2/position/__init__.py
demeter/gmx/gmx_v2/pricing/PositionPricingUtils.py
demeter/gmx/gmx_v2/pricing/SwapPricingUtils.py
demeter/gmx/gmx_v2/pricing/__init__.py
demeter/gmx/gmx_v2/reader/ReaderPositionUtils.py
demeter/gmx/gmx_v2/reader/ReaderPricingUtils.py
demeter/gmx/gmx_v2/reader/__init__.py
demeter/gmx/gmx_v2/swap/SwapUtils.py
zelos_demeter.egg-info/PKG-INFO
zelos_demeter.egg-info/SOURCES.txt
zelos_demeter.egg-info/dependency_links.txt
zelos_demeter.egg-info/requires.txt
zelos_demeter.egg-info/top_level.txt