Metadata-Version: 2.2
Name: zelos-demeter
Version: 1.2.0
Summary: better DEFI backtesting tool
Home-page: https://zelos-demeter.readthedocs.io
Author: zelos research
Author-email: zelos@antalpha.com
License: MIT
Requires-Python: >=3.11
License-File: LICENSE
Requires-Dist: numpy>=1.26.4
Requires-Dist: pandas>=2.2.0
Requires-Dist: python-dateutil>=2.9.0.post0
Requires-Dist: pytz>=2024.1
Requires-Dist: six>=1.16.0
Requires-Dist: db-dtypes>=1.2.0
Requires-Dist: tqdm>=4.66.2
Requires-Dist: orjson>=3.9.15
Dynamic: author
Dynamic: author-email
Dynamic: description
Dynamic: description-content-type
Dynamic: home-page
Dynamic: license
Dynamic: requires-dist
Dynamic: requires-python
Dynamic: summary
